README
setup.py
rich_base_provider/__init__.py
rich_base_provider/response.py
rich_base_provider/settings.py
rich_base_provider/utils.py
rich_base_provider.egg-info/PKG-INFO
rich_base_provider.egg-info/SOURCES.txt
rich_base_provider.egg-info/dependency_links.txt
rich_base_provider.egg-info/top_level.txt
rich_base_provider/sysadmin/__init__.py
rich_base_provider/sysadmin/coupon/__init__.py
rich_base_provider/sysadmin/coupon/models.py
rich_base_provider/sysadmin/coupon/views.py
rich_base_provider/sysadmin/integral/__init__.py
rich_base_provider/sysadmin/integral/integral_charge/__init__.py
rich_base_provider/sysadmin/integral/integral_charge/models.py
rich_base_provider/sysadmin/integral/integral_charge/views.py
rich_base_provider/sysadmin/integral/integral_charge_record/__init__.py
rich_base_provider/sysadmin/integral/integral_charge_record/models.py
rich_base_provider/sysadmin/integral/integral_charge_record/views.py
rich_base_provider/sysadmin/integral/integral_rule/__init__.py
rich_base_provider/sysadmin/integral/integral_rule/models.py
rich_base_provider/sysadmin/integral/integral_rule/views.py
rich_base_provider/sysadmin/pingan/__init__.py
rich_base_provider/sysadmin/pingan/pingan_until.py
rich_base_provider/sysadmin/recharge/__init__.py
rich_base_provider/sysadmin/recharge/balance_recharge_record/__init__.py
rich_base_provider/sysadmin/recharge/balance_recharge_record/models.py
rich_base_provider/sysadmin/recharge/balance_recharge_record/views.py
rich_base_provider/sysadmin/recharge/recharge_rule/__init__.py
rich_base_provider/sysadmin/recharge/recharge_rule/models.py
rich_base_provider/sysadmin/recharge/recharge_rule/views.py
rich_base_provider/sysadmin/sys_bin/__init__.py
rich_base_provider/sysadmin/sys_bin/views.py
rich_base_provider/sysadmin/sys_dict/__init__.py
rich_base_provider/sysadmin/sys_dict/models.py
rich_base_provider/sysadmin/sys_dict/views.py
rich_base_provider/sysadmin/sys_org/__init__.py
rich_base_provider/sysadmin/sys_org/models.py
rich_base_provider/sysadmin/sys_org/views.py
rich_base_provider/sysadmin/sys_org/views_org_center.py
rich_base_provider/sysadmin/sys_permission/__init__.py
