Metadata-Version: 1.2
Name: rich-base-provider
Version: 1.0.1
Summary: A Python Package Test
Home-page: https://www.python.org/
Author: yinchengping
Author-email: 339171112@qq.com
License: MIT
Keywords: ga nn
Platform: UNKNOWN
Requires-Python: >=3
